MANIFEST.in
NETWORK_ALIASES.md
README.md
ccm
setup.py
ccm.egg-info/PKG-INFO
ccm.egg-info/SOURCES.txt
ccm.egg-info/dependency_links.txt
ccm.egg-info/requires.txt
ccm.egg-info/top_level.txt
ccmlib/__init__.py
ccmlib/cluster.py
ccmlib/cluster_factory.py
ccmlib/common.py
ccmlib/dse_cluster.py
ccmlib/dse_node.py
ccmlib/extension.py
ccmlib/node.py
ccmlib/remote.py
ccmlib/repository.py
ccmlib/cmds/__init__.py
ccmlib/cmds/cluster_cmds.py
ccmlib/cmds/command.py
ccmlib/cmds/node_cmds.py