Metadata-Version: 1.1
Name: ccm
Version: 3.1.3
Summary: Cassandra Cluster Manager
Home-page: https://github.com/pcmanus/ccm
Author: Sylvain Lebresne
Author-email: sylvain@datastax.com
License: UNKNOWN
Platform: UNKNOWN
Classifier: License :: OSI Approved :: Apache Software License
Classifier: Programming Language :: Python
Classifier: Programming Language :: Python :: 2
Classifier: Programming Language :: Python :: 2.7
Classifier: Programming Language :: Python :: 3
Classifier: Programming Language :: Python :: 3.3
Classifier: Programming Language :: Python :: 3.4
Classifier: Programming Language :: Python :: 3.5
Classifier: Programming Language :: Python :: 3.6
